{
  "$schema": "https://schema.management.azure.com/schemas/2019-04-01/deploymentTemplate.json#",
  "contentVersion": "1.0.0.0",
  "metadata": {
    "_generator": {
      "name": "AzOps"
    }
  },
  "parameters": {},
  "variables": {},
  "resources": [
    {
      "type": "Microsoft.Automation/automationAccounts/jobs",
      "apiVersion": "2019-06-01",
      "name": "myaa33d/6b84fd82-8eb4-489c-a1ca-1ee11d62b3bb",
      "properties": {
        "runbook": {
          "name": "ScheduledStartStop_Child"
        }
      }
    }
  ],
  "outputs": {}
}
